[
    {
        "table_cols": [
            {
                "pri_key": true,
                "col_comment": "会员编号",
                "col_name": "member_no",
                "col_type": "char(32)"
            },
            {
                "col_comment": "会员卡号",
                "col_name": "card_no",
                "col_type": "varchar(30)",
                "allow_null": true
            },
            {
                "col_comment": "会员姓名",
                "col_name": "member_name",
                "col_type": "varchar(20)",
                "allow_null": true
            },
            {
                "col_comment": "会员手机号",
                "col_name": "member_tel",
                "col_type": "varchar(11)",
                "allow_null": true
            },
            {
                  "col_comment": "会员消费密码",
                  "col_name": "member_pwd",
                  "col_type": "varchar(11)",
                  "allow_null": true
            },
            {
                "col_comment": "会员充值总金额",
                "col_name": "member_expenses",
                "col_type": "int(11)",
                "default": 0
            },
            {
                "col_comment": "会员赠送总金额",
                "col_name": "sys_expenses",
                "col_type": "int(11)",
                "default": 0
            },
            {
                "col_comment": "会员剩余金额",
                "col_name": "member_balance",
                "col_type": "int(11)",
                "default": 0
            },
            {
                "col_comment": "会员剩余赠送金额",
                "col_name": "sys_balance",
                "col_type": "int(11)",
                "default": 0
            },
            {
                "col_comment": "会员积分",
                "col_name": "member_score",
                "col_type": "int(11)",
                "default": 0
            },
            {
                "col_comment": "更新时间",
                "col_name": "update_time",
                "col_type": "int(11)"
            },
            {
                "col_comment": "创建时间",
                "col_name": "join_time",
                "col_type": "int(11)"
            }
        ],
        "table_comment": "会员信息",
        "table_name": "member_info"
    }
]